aiopulsar/__init__.py
aiopulsar/client.py
aiopulsar/consumer.py
aiopulsar/producer.py
aiopulsar/reader.py
aiopulsar/utils.py
aiopulsar_py-0.1.0a0.dist-info/LICENSE
aiopulsar_py-0.1.0a0.dist-info/WHEEL
aiopulsar_py-0.1.0a0.dist-info/METADATA
aiopulsar_py-0.1.0a0.dist-info/RECORD
