Metadata-Version: 2.1
Name: aiopulsar-py
Version: 0.1.0a0
Summary: Asynchronous wrapper for the python pulsar-client.
Home-page: https://github.com/mads-hb/aiopulsar-py
License: Apache 2.0
Author: Mads Hansen Baattrup
Author-email: mads@baattrup.com
Requires-Python: >=3.7,<4.0
Classifier: Development Status :: 3 - Alpha
Classifier: Framework :: AsyncIO
Classifier: License :: Other/Proprietary License
Classifier: Operating System :: POSIX
Classifier: Programming Language :: Python :: 3
Classifier: Programming Language :: Python :: 3.7
Classifier: Programming Language :: Python :: 3.8
Classifier: Programming Language :: Python :: 3.9
Classifier: Programming Language :: Python :: 3.10
Classifier: Programming Language :: Python :: 3.11
Requires-Dist: pulsar-client (>=2.10.0)
Project-URL: Repository, https://github.com/mads-hb/aiopulsar-py
